[
  {
    "id": 1756485062791,
    "title": "Scene 2025. 8. 30. 오전 1:31:02",
    "globalCaption": "Generated scene",
    "instances": [
      {
        "id": "instance-ab7d5ca8-2c6c-48dd-93fc-5597cc64e4cd",
        "label": "man",
        "textDescription": "An old man wearing a gray cardigan with 2 buttons, black pants, and a beret, with short white hair, around 150 cm tall, looking at two men and a woman, and slightly overweight.",
        "sceneGraph": {
          "objects": [
            {
              "id": "object1",
              "name": "man",
              "attributes": [
                "old",
                "wearing gray cardigan with 2 buttons",
                "wearing black pants",
                "short white hair",
                "beret",
                "around 150 cm tall",
                "slightly overweight"
              ]
            },
            {
              "id": "object2",
              "name": "woman",
              "attributes": []
            },
            {
              "id": "6f8cc751-fe98-44fa-8d74-4f7620b8d75c",
              "name": "man",
              "attributes": []
            }
          ],
          "relationships": [
            {
              "source": "object1",
              "target": "object2",
              "relation": "looking at"
            },
            {
              "source": "object1",
              "target": "6f8cc751-fe98-44fa-8d74-4f7620b8d75c",
              "relation": "looking at"
            }
          ],
          "root": "object1"
        },
        "boundingBox": {
          "x": 5,
          "y": 290,
          "width": 78,
          "height": 203
        },
        "isFromClass": false
      },
      {
        "id": "instance-ab338629-bc4f-400f-a568-36c97fe5380a",
        "label": "woman",
        "textDescription": "A 35-year-old woman with short white hair wearing a beret. She is chubby and around 165 cm tall, dressed in a short sleeve dress with pink and blue flower patterns and black pants.",
        "sceneGraph": {
          "objects": [
            {
              "id": "object1",
              "name": "woman",
              "attributes": [
                "35-year-old",
                "wearing black pants",
                "shot sleeve dress has pink and blue flower patterns",
                "white short hair with beret",
                "around 165, chubby",
                "DELETE",
                "female"
              ]
            }
          ],
          "relationships": [],
          "root": "object1"
        },
        "boundingBox": {
          "x": 121,
          "y": 224,
          "width": 123,
          "height": 288
        },
        "isFromClass": false
      },
      {
        "id": "instance-7c5215ca-bbe5-455a-a350-9b0688323cb3",
        "label": "male",
        "textDescription": "A 35-year-old male wearing a short-sleeved blue polo shirt, knee-length beige shorts, and black slippers, with curly short black hair and without a hat.",
        "sceneGraph": {
          "objects": [
            {
              "id": "object1",
              "name": "male",
              "attributes": [
                "35-year-old",
                "wearing knee length beige shorts",
                "male",
                "without hat",
                "short sleeved blue polo shirt",
                "curly short hair",
                "black slippers"
              ]
            }
          ],
          "relationships": [],
          "root": "object1"
        },
        "boundingBox": {
          "x": 254,
          "y": 193,
          "width": 95,
          "height": 319
        },
        "isFromClass": false
      },
      {
        "id": "instance-fcda1753-e5eb-4e29-a685-63f29a6d30ef",
        "label": "girl",
        "textDescription": "A 7-year-old girl with short hair wearing a neon pink sleeveless top with a white small patch on the left chest, a white puffy skirt, and pink sneakers.",
        "sceneGraph": {
          "objects": [
            {
              "id": "object1",
              "name": "girl",
              "attributes": [
                "7-year-old",
                "wearing neon pink sleeveless with white small patch on left chest",
                "pink sneakers",
                "100",
                "short hair",
                "wearing white puffy skirt",
                "female"
              ]
            }
          ],
          "relationships": [],
          "root": "object1"
        },
        "boundingBox": {
          "x": 375,
          "y": 373,
          "width": 100,
          "height": 122
        },
        "isFromClass": false
      },
      {
        "id": "instance-4c28e218-f058-4e6c-ad45-814301dafbc5",
        "label": "balloon",
        "textDescription": "a yellow balloon",
        "sceneGraph": {
          "objects": [
            {
              "id": "object1",
              "name": "balloon",
              "attributes": [
                "yellow"
              ]
            }
          ],
          "relationships": [],
          "root": "object1"
        },
        "boundingBox": {
          "x": 455,
          "y": 258,
          "width": 50,
          "height": 50
        },
        "isFromClass": false
      },
      {
        "id": "instance-009f6070-6e27-44cc-bfdc-115e2896c840",
        "label": "bear",
        "textDescription": "a teddy bear",
        "sceneGraph": {
          "objects": [
            {
              "id": "object1",
              "name": "bear",
              "attributes": [
                "teddy"
              ]
            }
          ],
          "relationships": [],
          "root": "object1"
        },
        "boundingBox": {
          "x": 350,
          "y": 428,
          "width": 50,
          "height": 49
        },
        "isFromClass": false
      },
      {
        "id": "instance-7277b5cd-e9c3-4130-a9eb-9176271037d3",
        "label": "tray",
        "textDescription": "a tray full of disposable bottles of water",
        "sceneGraph": {
          "objects": [
            {
              "id": "object1",
              "name": "tray",
              "attributes": [
                "full"
              ]
            },
            {
              "id": "object2",
              "name": "bottle",
              "attributes": [
                "disposable",
                "of",
                "water"
              ]
            }
          ],
          "relationships": [
            {
              "source": "object1",
              "target": "object2",
              "relation": "contains"
            }
          ],
          "root": "object1"
        },
        "boundingBox": {
          "x": 383,
          "y": 185,
          "width": 50,
          "height": 50
        },
        "isFromClass": false
      },
      {
        "id": "instance-72b52b15-04fc-4e65-bcdd-0f41da009564",
        "label": "basket",
        "textDescription": "a basket with a few items in it",
        "sceneGraph": {
          "objects": [
            {
              "id": "object1",
              "name": "basket",
              "attributes": []
            },
            {
              "id": "object2",
              "name": "item",
              "attributes": [
                "few"
              ]
            }
          ],
          "relationships": [
            {
              "source": "object1",
              "target": "object2",
              "relation": "with"
            }
          ],
          "root": "object1"
        },
        "boundingBox": {
          "x": 211,
          "y": 338,
          "width": 50,
          "height": 50
        },
        "isFromClass": false
      }
    ],
    "sceneGraph": {
      "relationships": [
        {
          "type": "spatial",
          "from": "instance-fcda1753-e5eb-4e29-a685-63f29a6d30ef",
          "to": "instance-4c28e218-f058-4e6c-ad45-814301dafbc5",
          "relationship": "girl Is holding balloon in left hand"
        },
        {
          "type": "spatial",
          "from": "instance-009f6070-6e27-44cc-bfdc-115e2896c840",
          "to": "instance-fcda1753-e5eb-4e29-a685-63f29a6d30ef",
          "relationship": "holding tedyy on she's right hand"
        },
        {
          "type": "spatial",
          "from": "instance-7277b5cd-e9c3-4130-a9eb-9176271037d3",
          "to": "instance-7c5215ca-bbe5-455a-a350-9b0688323cb3",
          "relationship": "related"
        },
        {
          "type": "spatial",
          "from": "instance-72b52b15-04fc-4e65-bcdd-0f41da009564",
          "to": "instance-ab338629-bc4f-400f-a568-36c97fe5380a",
          "relationship": "holding basket with the man"
        },
        {
          "type": "spatial",
          "from": "instance-72b52b15-04fc-4e65-bcdd-0f41da009564",
          "to": "instance-7c5215ca-bbe5-455a-a350-9b0688323cb3",
          "relationship": "holding basket with the woman"
        }
      ]
    },
    "exportedAt": "2025-08-29T16:31:02.791Z",
    "nodeCount": 8,
    "edgeCount": 5
  }
]